HWS/HSM_Utils.py
HWS/HSM_WFN.py
HWS/HS_Anomalies.py
HWS/HS_BeamProfile.py
HWS/HS_CamConfig.py
HWS/HS_Camera.py
HWS/HS_Centroids.py
HWS/HS_Export.py
HWS/HS_GaussianBeam.py
HWS/HS_GaussianWF.py
HWS/HS_Gradients.py
HWS/HS_Image.py
HWS/HS_OFF2ON.py
HWS/HS_PV.py
HWS/HS_WFP.py
HWS/__init__.py
HWS/_version.py
hws-2.1.0.dist-info/LICENSE.md
hws-2.1.0.dist-info/METADATA
hws-2.1.0.dist-info/WHEEL
hws-2.1.0.dist-info/top_level.txt
hws-2.1.0.dist-info/RECORD
