Metadata-Version: 2.1
Name: hws
Version: 2.1.0
Summary: Python toolbox for analysing Hartmann Wavefront sensor data for the LIGO and Virgo detectors
Home-page: https://git.ligo.org/HWS/hws
Author-email: peter.veitch@adelaide.edu.au
License: GPL
Project-URL: Bug Tracker, https://git.ligo.org/HWS/hws/issues
Project-URL: Source Code, https://git.ligo.org/HWS/hws
Classifier: Topic :: Scientific/Engineering :: Physics
Classifier: Intended Audience :: Science/Research
Classifier: Natural Language :: English
Classifier: License :: OSI Approved :: GNU General Public License v3 or later (GPLv3+)
Classifier: Operating System :: Microsoft :: Windows
Classifier: Operating System :: POSIX
Classifier: Operating System :: Unix
Classifier: Operating System :: MacOS
Classifier: Programming Language :: Python :: 3
Requires-Python: >=3.6
License-File: LICENSE.md
Requires-Dist: numpy
Requires-Dist: scipy
Requires-Dist: matplotlib
Requires-Dist: h5py
Requires-Dist: scikit-image
